{
    "normal": {
        "added": [
            "ext__MemberACPManagement",
            "reg_welcome_email",
            "reg_welcome_email_desc",
            "reg_welcome_email_text",
            "menu__core_clubs_templates",
            "dev_acpsearch_callback",
            "dev_acpsearch_callback_desc",
            "statsreports_update_filters"
        ],
        "edited": [],
        "removed": [
            "mennu__core_clubs_templates",
            "dev_widget_area",
            "dev_widget_default_area",
            "dev_widget_default_area_desc",
            "dev_widget_default_area_header",
            "dev_widget_default_area_footer",
            "dev_widget_default_area_sidebar"
        ]
    },
    "js": {
        "added": [
            "editor_code--ipsplaintext"
        ],
        "edited": [],
        "removed": []
    }
}